{"targets": {"0": {"-1": 0.424, "0": 0.002, "1": 0.574}, "1": {"-1": 0.318, "0": 0.002, "1": 0.68}, "2": {"-1": 0.492, "0": 0.0, "1": 0.508}, "3": {"-1": 0, "0": 0, "1": 0}, "4": {"-1": 0.43, "0": 0.002, "1": 0.568}, "5": {"-1": 0.492, "0": 0.002, "1": 0.506}, "6": {"-1": 0.512, "0": 0.002, "1": 0.486}}, "board": [[0.0, 0.0, 0.0, -1.0, 0.0, 0.0, 0.0], [0.0, 0.0, 0.0, -1.0, 0.0, 0.0, 0.0], [0.0, 0.0, 0.0, 1.0, 0.0, 1.0, 0.0], [0.0, 1.0, 0.0, -1.0, 0.0, -1.0, 0.0], [0.0, 1.0, 0.0, -1.0, 1.0, -1.0, 0.0], [1.0, -1.0, 0.0, 1.0, -1.0, 1.0, 0.0]]}