{"targets": {"0": {"-1": 0.498, "0": 0.068, "1": 0.434}, "1": {"-1": 0, "0": 0, "1": 0}, "2": {"-1": 0.072, "0": 0.126, "1": 0.802}, "3": {"-1": 0.532, "0": 0.072, "1": 0.396}, "4": {"-1": 0.0, "0": 0.0, "1": 1.0}, "5": {"-1": 0.494, "0": 0.0, "1": 0.506}, "6": {"-1": 0.512, "0": 0.07, "1": 0.418}}, "board": [[0.0, 1.0, 0.0, 0.0, 0.0, 0.0, 0.0], [0.0, 1.0, 0.0, -1.0, 0.0, 0.0, -1.0], [-1.0, -1.0, 0.0, 1.0, 1.0, 0.0, -1.0], [1.0, -1.0, 1.0, -1.0, -1.0, -1.0, 1.0], [-1.0, 1.0, -1.0, 1.0, 1.0, 1.0, -1.0], [-1.0, 1.0, 1.0, 1.0, -1.0, 1.0, -1.0]]}