{"targets": {"0": {"-1": 0.29, "0": 0.004, "1": 0.706}, "1": {"-1": 0.246, "0": 0.01, "1": 0.744}, "2": {"-1": 0.254, "0": 0.008, "1": 0.738}, "3": {"-1": 0.0, "0": 0.0, "1": 1.0}, "4": {"-1": 0.224, "0": 0.004, "1": 0.772}, "5": {"-1": 0.302, "0": 0.002, "1": 0.696}, "6": {"-1": 0.084, "0": 0.012, "1": 0.904}}, "board": [[0.0, 0.0, 0.0, 0.0, 0.0, 0.0, 0.0], [1.0, 0.0, 0.0, 0.0, 0.0, -1.0, 0.0], [-1.0, -1.0, 0.0, 0.0, 0.0, -1.0, 0.0], [1.0, -1.0, -1.0, 0.0, 0.0, 1.0, 1.0], [1.0, 1.0, 1.0, 0.0, 0.0, -1.0, 1.0], [-1.0, -1.0, -1.0, 1.0, 1.0, 1.0, -1.0]]}