{"targets": {"0": {"-1": 0.802, "0": 0.004, "1": 0.194}, "1": {"-1": 0.598, "0": 0.01, "1": 0.392}, "2": {"-1": 0.516, "0": 0.012, "1": 0.472}, "3": {"-1": 0.728, "0": 0.0, "1": 0.272}, "4": {"-1": 0.658, "0": 0.0, "1": 0.342}, "5": {"-1": 0.628, "0": 0.004, "1": 0.368}, "6": {"-1": 0.764, "0": 0.01, "1": 0.226}}, "board": [[0.0, 0.0, 0.0, 0.0, 0.0, 0.0, 0.0], [0.0, -1.0, 0.0, 0.0, 0.0, 0.0, 0.0], [-1.0, -1.0, 0.0, 0.0, 0.0, 0.0, 0.0], [1.0, -1.0, 1.0, -1.0, 1.0, 1.0, -1.0], [-1.0, 1.0, 1.0, 1.0, -1.0, 1.0, 1.0], [-1.0, 1.0, -1.0, 1.0, 1.0, -1.0, -1.0]]}