{"targets": {"0": {"-1": 0.1, "0": 0.036, "1": 0.864}, "1": {"-1": 0.0, "0": 0.0, "1": 1.0}, "2": {"-1": 0, "0": 0, "1": 0}, "3": {"-1": 0.0, "0": 0.0, "1": 1.0}, "4": {"-1": 0.07, "0": 0.062, "1": 0.868}, "5": {"-1": 0.126, "0": 0.04, "1": 0.834}, "6": {"-1": 0.094, "0": 0.026, "1": 0.88}}, "board": [[0.0, 0.0, -1.0, 0.0, 0.0, 0.0, 0.0], [0.0, 1.0, 1.0, 1.0, -1.0, -1.0, 0.0], [0.0, 1.0, -1.0, 1.0, -1.0, 1.0, 0.0], [-1.0, -1.0, -1.0, 1.0, 1.0, 1.0, -1.0], [1.0, 1.0, 1.0, -1.0, 1.0, -1.0, -1.0], [-1.0, 1.0, -1.0, -1.0, -1.0, 1.0, 1.0]]}