{"targets": {"0": {"-1": 0.808, "0": 0.0, "1": 0.192}, "1": {"-1": 0.756, "0": 0.0, "1": 0.244}, "2": {"-1": 0.664, "0": 0.0, "1": 0.336}, "3": {"-1": 0.57, "0": 0.0, "1": 0.43}, "4": {"-1": 0.794, "0": 0.0, "1": 0.206}, "5": {"-1": 0.852, "0": 0.002, "1": 0.146}, "6": {"-1": 0.858, "0": 0.002, "1": 0.14}}, "board": [[0.0, 0.0, 0.0, 0.0, 0.0, 0.0, 0.0], [0.0, 0.0, 0.0, 0.0, 0.0, 1.0, 0.0], [0.0, 0.0, 0.0, 0.0, 0.0, 1.0, 0.0], [0.0, 1.0, 0.0, 0.0, 0.0, -1.0, 0.0], [0.0, -1.0, -1.0, 0.0, -1.0, -1.0, 0.0], [1.0, 1.0, -1.0, -1.0, 1.0, 1.0, 0.0]]}