{"targets": {"0": {"-1": 0.77, "0": 0.044, "1": 0.186}, "1": {"-1": 0.846, "0": 0.104, "1": 0.05}, "2": {"-1": 0.932, "0": 0.028, "1": 0.04}, "3": {"-1": 0.72, "0": 0.15, "1": 0.13}, "4": {"-1": 0.902, "0": 0.048, "1": 0.05}, "5": {"-1": 0.9, "0": 0.056, "1": 0.044}, "6": {"-1": 0.892, "0": 0.06, "1": 0.048}}, "board": [[0.0, 0.0, 0.0, 0.0, 0.0, 0.0, 0.0], [1.0, 0.0, -1.0, 0.0, 1.0, -1.0, 0.0], [1.0, 0.0, 1.0, -1.0, -1.0, 1.0, 0.0], [-1.0, -1.0, 1.0, 1.0, -1.0, -1.0, -1.0], [1.0, 1.0, 1.0, -1.0, -1.0, 1.0, -1.0], [1.0, -1.0, -1.0, 1.0, 1.0, -1.0, 1.0]]}