{"targets": {"0": {"-1": 0.724, "0": 0.0, "1": 0.276}, "1": {"-1": 0.752, "0": 0.0, "1": 0.248}, "2": {"-1": 0.474, "0": 0.0, "1": 0.526}, "3": {"-1": 0.688, "0": 0.0, "1": 0.312}, "4": {"-1": 0.508, "0": 0.0, "1": 0.492}, "5": {"-1": 0.484, "0": 0.0, "1": 0.516}, "6": {"-1": 0.666, "0": 0.0, "1": 0.334}}, "board": [[0.0, 0.0, 0.0, 0.0, 0.0, 0.0, 0.0], [0.0, 0.0, 0.0, 1.0, 0.0, 0.0, 0.0], [0.0, 0.0, 0.0, 1.0, 0.0, 0.0, 0.0], [-1.0, 0.0, -1.0, -1.0, 0.0, 0.0, 0.0], [1.0, 0.0, -1.0, 1.0, 0.0, 0.0, 1.0], [1.0, -1.0, 1.0, 1.0, -1.0, -1.0, -1.0]]}