{"targets": {"0": {"-1": 0.624, "0": 0.116, "1": 0.26}, "1": {"-1": 0.61, "0": 0.128, "1": 0.262}, "2": {"-1": 0, "0": 0, "1": 0}, "3": {"-1": 0, "0": 0, "1": 0}, "4": {"-1": 0.834, "0": 0.166, "1": 0.0}, "5": {"-1": 0, "0": 0, "1": 0}, "6": {"-1": 0, "0": 0, "1": 0}}, "board": [[0.0, 0.0, 1.0, 1.0, 0.0, -1.0, 1.0], [1.0, -1.0, -1.0, -1.0, 0.0, 1.0, -1.0], [-1.0, -1.0, 1.0, 1.0, 0.0, -1.0, 1.0], [1.0, 1.0, 1.0, -1.0, 0.0, -1.0, 1.0], [1.0, -1.0, -1.0, 1.0, -1.0, -1.0, -1.0], [-1.0, 1.0, 1.0, 1.0, -1.0, 1.0, -1.0]]}