{"targets": {"0": {"-1": 0.488, "0": 0.0, "1": 0.512}, "1": {"-1": 0.522, "0": 0.0, "1": 0.478}, "2": {"-1": 0.494, "0": 0.0, "1": 0.506}, "3": {"-1": 0.516, "0": 0.0, "1": 0.484}, "4": {"-1": 0.492, "0": 0.0, "1": 0.508}, "5": {"-1": 0.518, "0": 0.0, "1": 0.482}, "6": {"-1": 0.434, "0": 0.0, "1": 0.566}}, "board": [[0.0, 0.0, 0.0, 0.0, 0.0, 0.0, 0.0], [0.0, 0.0, 0.0, 0.0, 0.0, 0.0, 0.0], [1.0, 1.0, 0.0, 1.0, 0.0, 0.0, 0.0], [-1.0, -1.0, 0.0, -1.0, -1.0, 0.0, 0.0], [-1.0, -1.0, 0.0, 1.0, 1.0, 0.0, -1.0], [1.0, 1.0, -1.0, -1.0, 1.0, 0.0, 1.0]]}