{"targets": {"0": {"-1": 0.892, "0": 0.028, "1": 0.08}, "1": {"-1": 0.77, "0": 0.004, "1": 0.226}, "2": {"-1": 0.876, "0": 0.006, "1": 0.118}, "3": {"-1": 0.86, "0": 0.018, "1": 0.122}, "4": {"-1": 0.854, "0": 0.03, "1": 0.116}, "5": {"-1": 0.774, "0": 0.032, "1": 0.194}, "6": {"-1": 0.848, "0": 0.022, "1": 0.13}}, "board": [[0.0, 0.0, 0.0, 0.0, 0.0, 0.0, 0.0], [1.0, 0.0, 0.0, -1.0, 1.0, 0.0, 0.0], [1.0, 1.0, 0.0, -1.0, 1.0, 0.0, -1.0], [-1.0, -1.0, 0.0, 1.0, -1.0, 0.0, -1.0], [1.0, 1.0, 1.0, -1.0, 1.0, 0.0, 1.0], [1.0, -1.0, -1.0, 1.0, -1.0, -1.0, -1.0]]}