{"targets": {"0": {"-1": 0.55, "0": 0.0, "1": 0.45}, "1": {"-1": 0.39, "0": 0.0, "1": 0.61}, "2": {"-1": 0.318, "0": 0.0, "1": 0.682}, "3": {"-1": 0.0, "0": 0.0, "1": 1.0}, "4": {"-1": 0.0, "0": 0.0, "1": 1.0}, "5": {"-1": 0.37, "0": 0.0, "1": 0.63}, "6": {"-1": 0.388, "0": 0.0, "1": 0.612}}, "board": [[0.0, 0.0, 0.0, 0.0, 0.0, 0.0, 0.0], [0.0, 1.0, 0.0, 0.0, 0.0, 0.0, -1.0], [0.0, -1.0, 0.0, 0.0, 0.0, 0.0, 1.0], [0.0, -1.0, 0.0, 0.0, 1.0, 1.0, 1.0], [-1.0, 1.0, -1.0, -1.0, 1.0, -1.0, 1.0], [1.0, -1.0, -1.0, -1.0, 1.0, 1.0, -1.0]]}