{"targets": {"0": {"-1": 0.414, "0": 0.006, "1": 0.58}, "1": {"-1": 0.178, "0": 0.014, "1": 0.808}, "2": {"-1": 0.0, "0": 0.0, "1": 1.0}, "3": {"-1": 0.242, "0": 0.01, "1": 0.748}, "4": {"-1": 0.0, "0": 0.0, "1": 1.0}, "5": {"-1": 0.354, "0": 0.006, "1": 0.64}, "6": {"-1": 0.39, "0": 0.002, "1": 0.608}}, "board": [[0.0, 0.0, 0.0, 0.0, 0.0, 0.0, 0.0], [0.0, 0.0, 0.0, 0.0, 0.0, 1.0, 0.0], [0.0, 0.0, 0.0, 1.0, 0.0, 1.0, 1.0], [0.0, -1.0, -1.0, 1.0, 1.0, -1.0, -1.0], [0.0, -1.0, 1.0, -1.0, 1.0, 1.0, -1.0], [0.0, 1.0, -1.0, -1.0, -1.0, 1.0, -1.0]]}