{"targets": {"0": {"-1": 0.332, "0": 0.06, "1": 0.608}, "1": {"-1": 0.48, "0": 0.014, "1": 0.506}, "2": {"-1": 0, "0": 0, "1": 0}, "3": {"-1": 0.144, "0": 0.012, "1": 0.844}, "4": {"-1": 0, "0": 0, "1": 0}, "5": {"-1": 0.46, "0": 0.038, "1": 0.502}, "6": {"-1": 0.382, "0": 0.034, "1": 0.584}}, "board": [[0.0, 0.0, 1.0, 0.0, -1.0, 0.0, 0.0], [0.0, 0.0, -1.0, 0.0, 1.0, 1.0, 0.0], [-1.0, 0.0, 1.0, 0.0, 1.0, -1.0, 0.0], [-1.0, 0.0, -1.0, 0.0, -1.0, 1.0, 0.0], [1.0, 0.0, -1.0, 1.0, -1.0, 1.0, 1.0], [1.0, -1.0, 1.0, 1.0, -1.0, -1.0, -1.0]]}