{"targets": {"0": {"-1": 0.966, "0": 0.0, "1": 0.034}, "1": {"-1": 0, "0": 0, "1": 0}, "2": {"-1": 0.754, "0": 0.0, "1": 0.246}, "3": {"-1": 0.892, "0": 0.0, "1": 0.108}, "4": {"-1": 0.912, "0": 0.0, "1": 0.088}, "5": {"-1": 0, "0": 0, "1": 0}, "6": {"-1": 0, "0": 0, "1": 0}}, "board": [[0.0, 1.0, 0.0, 0.0, 0.0, 1.0, 1.0], [0.0, 1.0, 0.0, 0.0, -1.0, -1.0, -1.0], [0.0, -1.0, 0.0, 0.0, -1.0, 1.0, 1.0], [0.0, 1.0, -1.0, 0.0, -1.0, -1.0, 1.0], [-1.0, -1.0, -1.0, 1.0, 1.0, -1.0, -1.0], [1.0, 1.0, 1.0, -1.0, 1.0, 1.0, -1.0]]}