{"targets": {"0": {"-1": 0.322, "0": 0.01, "1": 0.668}, "1": {"-1": 0.432, "0": 0.004, "1": 0.564}, "2": {"-1": 0.43, "0": 0.008, "1": 0.562}, "3": {"-1": 0.314, "0": 0.016, "1": 0.67}, "4": {"-1": 0, "0": 0, "1": 0}, "5": {"-1": 0.35, "0": 0.018, "1": 0.632}, "6": {"-1": 0, "0": 0, "1": 0}}, "board": [[0.0, 0.0, 0.0, 0.0, 1.0, 0.0, -1.0], [0.0, 0.0, 0.0, 0.0, -1.0, 0.0, 1.0], [0.0, 0.0, -1.0, 0.0, 1.0, -1.0, 1.0], [0.0, 1.0, 1.0, 0.0, 1.0, -1.0, 1.0], [-1.0, -1.0, 1.0, 0.0, -1.0, 1.0, -1.0], [-1.0, 1.0, -1.0, -1.0, -1.0, 1.0, 1.0]]}