{"targets": {"0": {"-1": 0.526, "0": 0.014, "1": 0.46}, "1": {"-1": 0.504, "0": 0.012, "1": 0.484}, "2": {"-1": 0.226, "0": 0.03, "1": 0.744}, "3": {"-1": 0.0, "0": 0.0, "1": 1.0}, "4": {"-1": 0.52, "0": 0.016, "1": 0.464}, "5": {"-1": 0.312, "0": 0.004, "1": 0.684}, "6": {"-1": 0.408, "0": 0.014, "1": 0.578}}, "board": [[0.0, 0.0, 0.0, 0.0, 0.0, 0.0, 0.0], [0.0, 0.0, 0.0, 0.0, 0.0, 0.0, 0.0], [0.0, 1.0, 0.0, 0.0, 0.0, 0.0, 0.0], [-1.0, -1.0, -1.0, 1.0, 1.0, 0.0, 0.0], [-1.0, 1.0, -1.0, 1.0, -1.0, 1.0, -1.0], [1.0, -1.0, -1.0, 1.0, -1.0, 1.0, 1.0]]}