{"targets": {"0": {"-1": 0.728, "0": 0.0, "1": 0.272}, "1": {"-1": 0.0, "0": 0.0, "1": 1.0}, "2": {"-1": 0, "0": 0, "1": 0}, "3": {"-1": 0, "0": 0, "1": 0}, "4": {"-1": 0.398, "0": 0.0, "1": 0.602}, "5": {"-1": 0.758, "0": 0.0, "1": 0.242}, "6": {"-1": 0, "0": 0, "1": 0}}, "board": [[0.0, 0.0, 1.0, 1.0, 0.0, 0.0, -1.0], [-1.0, 0.0, -1.0, -1.0, 0.0, -1.0, -1.0], [-1.0, 1.0, -1.0, -1.0, 1.0, -1.0, 1.0], [1.0, 1.0, 1.0, -1.0, 1.0, 1.0, -1.0], [1.0, 1.0, -1.0, 1.0, -1.0, 1.0, -1.0], [1.0, -1.0, 1.0, 1.0, -1.0, 1.0, -1.0]]}