{"targets": {"0": {"-1": 0.564, "0": 0.008, "1": 0.428}, "1": {"-1": 0.638, "0": 0.016, "1": 0.346}, "2": {"-1": 0.72, "0": 0.024, "1": 0.256}, "3": {"-1": 0.748, "0": 0.002, "1": 0.25}, "4": {"-1": 0.848, "0": 0.008, "1": 0.144}, "5": {"-1": 0.738, "0": 0.014, "1": 0.248}, "6": {"-1": 0, "0": 0, "1": 0}}, "board": [[0.0, 0.0, 0.0, 0.0, 0.0, 0.0, -1.0], [0.0, 0.0, 0.0, 0.0, 0.0, 0.0, 1.0], [0.0, 0.0, 0.0, 1.0, 0.0, 0.0, -1.0], [0.0, 0.0, 0.0, -1.0, 0.0, 0.0, 1.0], [1.0, -1.0, -1.0, -1.0, 0.0, -1.0, -1.0], [1.0, 1.0, 1.0, -1.0, 0.0, 1.0, 1.0]]}