{"targets": {"0": {"-1": 0.952, "0": 0.0, "1": 0.048}, "1": {"-1": 0, "0": 0, "1": 0}, "2": {"-1": 0.964, "0": 0.0, "1": 0.036}, "3": {"-1": 0.97, "0": 0.0, "1": 0.03}, "4": {"-1": 0.908, "0": 0.0, "1": 0.092}, "5": {"-1": 0.962, "0": 0.0, "1": 0.038}, "6": {"-1": 0.802, "0": 0.0, "1": 0.198}}, "board": [[0.0, 1.0, 0.0, 0.0, 0.0, 0.0, 0.0], [0.0, 1.0, 0.0, 0.0, 0.0, 0.0, 0.0], [0.0, -1.0, 0.0, 0.0, -1.0, 0.0, 0.0], [0.0, 1.0, 0.0, -1.0, -1.0, -1.0, 0.0], [0.0, -1.0, 0.0, 1.0, -1.0, -1.0, 1.0], [1.0, 1.0, -1.0, -1.0, 1.0, 1.0, 1.0]]}