{"targets": {"0": {"-1": 0.584, "0": 0.0, "1": 0.416}, "1": {"-1": 0, "0": 0, "1": 0}, "2": {"-1": 0.344, "0": 0.002, "1": 0.654}, "3": {"-1": 0.71, "0": 0.0, "1": 0.29}, "4": {"-1": 0.556, "0": 0.0, "1": 0.444}, "5": {"-1": 0.616, "0": 0.002, "1": 0.382}, "6": {"-1": 0.0, "0": 0.0, "1": 1.0}}, "board": [[0.0, 1.0, 0.0, 0.0, 0.0, 0.0, 0.0], [0.0, -1.0, 0.0, 0.0, 0.0, 0.0, 0.0], [0.0, 1.0, 0.0, 1.0, -1.0, 0.0, 0.0], [-1.0, 1.0, 0.0, -1.0, -1.0, 0.0, 0.0], [1.0, -1.0, 0.0, 1.0, -1.0, 1.0, 0.0], [-1.0, -1.0, -1.0, 1.0, 1.0, 1.0, 0.0]]}