{"targets": {"0": {"-1": 0.834, "0": 0.008, "1": 0.158}, "1": {"-1": 0.79, "0": 0.0, "1": 0.21}, "2": {"-1": 0.762, "0": 0.004, "1": 0.234}, "3": {"-1": 0.708, "0": 0.0, "1": 0.292}, "4": {"-1": 0.532, "0": 0.004, "1": 0.464}, "5": {"-1": 0.75, "0": 0.004, "1": 0.246}, "6": {"-1": 0.774, "0": 0.002, "1": 0.224}}, "board": [[0.0, 0.0, 0.0, 0.0, 0.0, 0.0, 0.0], [-1.0, 0.0, 0.0, 0.0, 0.0, 0.0, 0.0], [1.0, 0.0, 0.0, 0.0, 0.0, 0.0, 0.0], [-1.0, 0.0, 0.0, 0.0, -1.0, 1.0, 0.0], [1.0, 0.0, -1.0, 1.0, -1.0, -1.0, 1.0], [1.0, -1.0, 1.0, 1.0, -1.0, 1.0, -1.0]]}