{"targets": {"0": {"-1": 0.182, "0": 0.05, "1": 0.768}, "1": {"-1": 0.398, "0": 0.014, "1": 0.588}, "2": {"-1": 0.478, "0": 0.02, "1": 0.502}, "3": {"-1": 0.0, "0": 0.0, "1": 1.0}, "4": {"-1": 0.452, "0": 0.034, "1": 0.514}, "5": {"-1": 0.0, "0": 0.0, "1": 1.0}, "6": {"-1": 0.438, "0": 0.03, "1": 0.532}}, "board": [[0.0, 0.0, 0.0, 0.0, 0.0, 0.0, 0.0], [-1.0, 0.0, 0.0, 1.0, 1.0, 0.0, 0.0], [-1.0, 0.0, 0.0, -1.0, -1.0, 1.0, -1.0], [-1.0, 0.0, 0.0, 1.0, -1.0, 1.0, 1.0], [1.0, -1.0, 0.0, -1.0, 1.0, 1.0, -1.0], [1.0, -1.0, 1.0, 1.0, 1.0, -1.0, -1.0]]}