{"targets": {"0": {"-1": 0.486, "0": 0.016, "1": 0.498}, "1": {"-1": 0.634, "0": 0.018, "1": 0.348}, "2": {"-1": 0.606, "0": 0.03, "1": 0.364}, "3": {"-1": 0, "0": 0, "1": 0}, "4": {"-1": 0.522, "0": 0.0, "1": 0.478}, "5": {"-1": 0.542, "0": 0.05, "1": 0.408}, "6": {"-1": 0, "0": 0, "1": 0}}, "board": [[0.0, 0.0, 0.0, 1.0, 0.0, 0.0, 1.0], [0.0, 1.0, 0.0, -1.0, 0.0, 0.0, -1.0], [0.0, -1.0, -1.0, 1.0, 0.0, 0.0, -1.0], [0.0, 1.0, 1.0, -1.0, 0.0, -1.0, 1.0], [1.0, -1.0, -1.0, -1.0, 1.0, -1.0, -1.0], [1.0, -1.0, 1.0, -1.0, 1.0, 1.0, 1.0]]}