{"targets": {"0": {"-1": 0.604, "0": 0.0, "1": 0.396}, "1": {"-1": 0.71, "0": 0.0, "1": 0.29}, "2": {"-1": 0.766, "0": 0.0, "1": 0.234}, "3": {"-1": 0.702, "0": 0.0, "1": 0.298}, "4": {"-1": 0.0, "0": 0.0, "1": 1.0}, "5": {"-1": 0.69, "0": 0.0, "1": 0.31}, "6": {"-1": 0.466, "0": 0.0, "1": 0.534}}, "board": [[0.0, 0.0, 0.0, 0.0, 0.0, 0.0, 0.0], [0.0, 1.0, 0.0, 0.0, 0.0, 1.0, -1.0], [0.0, -1.0, 0.0, -1.0, 0.0, -1.0, -1.0], [-1.0, -1.0, 0.0, 1.0, 0.0, 1.0, -1.0], [1.0, -1.0, 0.0, 1.0, 0.0, 1.0, 1.0], [-1.0, 1.0, 1.0, -1.0, -1.0, 1.0, 1.0]]}