{"targets": {"0": {"-1": 0.612, "0": 0.004, "1": 0.384}, "1": {"-1": 0.432, "0": 0.008, "1": 0.56}, "2": {"-1": 0.424, "0": 0.014, "1": 0.562}, "3": {"-1": 0.384, "0": 0.0, "1": 0.616}, "4": {"-1": 0.324, "0": 0.008, "1": 0.668}, "5": {"-1": 0.4, "0": 0.008, "1": 0.592}, "6": {"-1": 0.464, "0": 0.004, "1": 0.532}}, "board": [[0.0, 0.0, 0.0, 0.0, 0.0, 0.0, 0.0], [0.0, 0.0, 0.0, 0.0, 0.0, 0.0, 0.0], [0.0, -1.0, 0.0, 0.0, 1.0, 0.0, 0.0], [-1.0, -1.0, -1.0, 1.0, 1.0, -1.0, 0.0], [1.0, 1.0, 1.0, -1.0, -1.0, 1.0, 1.0], [1.0, -1.0, -1.0, 1.0, 1.0, -1.0, -1.0]]}