{"targets": {"0": {"-1": 0.774, "0": 0.204, "1": 0.022}, "1": {"-1": 0, "0": 0, "1": 0}, "2": {"-1": 0.508, "0": 0.4, "1": 0.092}, "3": {"-1": 0.558, "0": 0.344, "1": 0.098}, "4": {"-1": 0, "0": 0, "1": 0}, "5": {"-1": 0.318, "0": 0.35, "1": 0.332}, "6": {"-1": 0, "0": 0, "1": 0}}, "board": [[0.0, -1.0, 0.0, 0.0, 1.0, 0.0, -1.0], [1.0, 1.0, 0.0, -1.0, -1.0, 0.0, 1.0], [1.0, -1.0, 1.0, 1.0, -1.0, 0.0, -1.0], [-1.0, 1.0, -1.0, -1.0, 1.0, 0.0, 1.0], [-1.0, -1.0, 1.0, 1.0, -1.0, -1.0, -1.0], [1.0, -1.0, 1.0, -1.0, 1.0, 1.0, 1.0]]}