{"targets": {"0": {"-1": 0.0, "0": 0.0, "1": 1.0}, "1": {"-1": 0.434, "0": 0.01, "1": 0.556}, "2": {"-1": 0, "0": 0, "1": 0}, "3": {"-1": 0.0, "0": 0.0, "1": 1.0}, "4": {"-1": 0.13, "0": 0.004, "1": 0.866}, "5": {"-1": 0.372, "0": 0.002, "1": 0.626}, "6": {"-1": 0.358, "0": 0.004, "1": 0.638}}, "board": [[0.0, 0.0, -1.0, 0.0, 0.0, 0.0, 0.0], [0.0, 1.0, 1.0, 0.0, 0.0, 0.0, 0.0], [0.0, -1.0, 1.0, 0.0, -1.0, 0.0, 0.0], [0.0, 1.0, 1.0, 1.0, -1.0, 1.0, 1.0], [-1.0, -1.0, -1.0, 1.0, -1.0, -1.0, -1.0], [-1.0, -1.0, 1.0, 1.0, 1.0, -1.0, 1.0]]}