{"targets": {"0": {"-1": 0.522, "0": 0.0, "1": 0.478}, "1": {"-1": 0.144, "0": 0.0, "1": 0.856}, "2": {"-1": 0.61, "0": 0.0, "1": 0.39}, "3": {"-1": 0.506, "0": 0.0, "1": 0.494}, "4": {"-1": 0.558, "0": 0.0, "1": 0.442}, "5": {"-1": 0, "0": 0, "1": 0}, "6": {"-1": 0, "0": 0, "1": 0}}, "board": [[0.0, 0.0, 0.0, 0.0, 0.0, -1.0, -1.0], [0.0, 0.0, 1.0, 0.0, 0.0, -1.0, 1.0], [-1.0, 0.0, 1.0, 1.0, 0.0, 1.0, 1.0], [-1.0, 0.0, -1.0, -1.0, 0.0, 1.0, -1.0], [1.0, -1.0, -1.0, 1.0, 0.0, -1.0, -1.0], [-1.0, 1.0, 1.0, -1.0, 1.0, 1.0, 1.0]]}