{"targets": {"0": {"-1": 0.76, "0": 0.17, "1": 0.07}, "1": {"-1": 0.0, "0": 0.876, "1": 0.124}, "2": {"-1": 0, "0": 0, "1": 0}, "3": {"-1": 0, "0": 0, "1": 0}, "4": {"-1": 0, "0": 0, "1": 0}, "5": {"-1": 0.666, "0": 0.334, "1": 0.0}, "6": {"-1": 0, "0": 0, "1": 0}}, "board": [[0.0, 0.0, 1.0, 1.0, -1.0, 0.0, -1.0], [1.0, 0.0, -1.0, 1.0, 1.0, 0.0, -1.0], [1.0, 0.0, -1.0, -1.0, -1.0, 1.0, 1.0], [-1.0, 1.0, -1.0, 1.0, 1.0, -1.0, -1.0], [-1.0, -1.0, 1.0, 1.0, -1.0, -1.0, 1.0], [1.0, 1.0, -1.0, -1.0, 1.0, 1.0, -1.0]]}