{"targets": {"0": {"-1": 0.818, "0": 0.0, "1": 0.182}, "1": {"-1": 0.828, "0": 0.0, "1": 0.172}, "2": {"-1": 0.674, "0": 0.0, "1": 0.326}, "3": {"-1": 0.604, "0": 0.0, "1": 0.396}, "4": {"-1": 0.0, "0": 0.0, "1": 1.0}, "5": {"-1": 0.0, "0": 0.0, "1": 1.0}, "6": {"-1": 0.73, "0": 0.0, "1": 0.27}}, "board": [[0.0, 0.0, 0.0, 0.0, 0.0, 0.0, 0.0], [1.0, 1.0, -1.0, 0.0, 0.0, 0.0, -1.0], [1.0, 1.0, -1.0, 1.0, 1.0, -1.0, -1.0], [-1.0, -1.0, -1.0, 1.0, 1.0, -1.0, -1.0], [-1.0, -1.0, 1.0, -1.0, 1.0, 1.0, 1.0], [1.0, -1.0, 1.0, 1.0, -1.0, 1.0, -1.0]]}