{"targets": {"0": {"-1": 0.37, "0": 0.012, "1": 0.618}, "1": {"-1": 0.252, "0": 0.01, "1": 0.738}, "2": {"-1": 0.304, "0": 0.02, "1": 0.676}, "3": {"-1": 0.0, "0": 0.0, "1": 1.0}, "4": {"-1": 0.374, "0": 0.016, "1": 0.61}, "5": {"-1": 0.346, "0": 0.0, "1": 0.654}, "6": {"-1": 0.0, "0": 0.0, "1": 1.0}}, "board": [[0.0, 0.0, 0.0, 0.0, 0.0, 0.0, 0.0], [-1.0, 0.0, -1.0, 0.0, 0.0, 1.0, 0.0], [-1.0, 0.0, 1.0, 0.0, 1.0, -1.0, 0.0], [1.0, 0.0, -1.0, 0.0, -1.0, 1.0, -1.0], [-1.0, -1.0, 1.0, 1.0, 1.0, -1.0, -1.0], [1.0, -1.0, 1.0, 1.0, 1.0, -1.0, 1.0]]}