{"targets": {"0": {"-1": 0.0, "0": 0.0, "1": 1.0}, "1": {"-1": 0.434, "0": 0.05, "1": 0.516}, "2": {"-1": 0.0, "0": 0.0, "1": 1.0}, "3": {"-1": 0.422, "0": 0.04, "1": 0.538}, "4": {"-1": 0, "0": 0, "1": 0}, "5": {"-1": 0.418, "0": 0.018, "1": 0.564}, "6": {"-1": 0.11, "0": 0.08, "1": 0.81}}, "board": [[0.0, 0.0, 0.0, 0.0, -1.0, 0.0, 0.0], [0.0, -1.0, 0.0, 1.0, 1.0, 0.0, 0.0], [0.0, 1.0, 0.0, -1.0, -1.0, -1.0, 0.0], [0.0, -1.0, 0.0, 1.0, 1.0, 1.0, -1.0], [0.0, 1.0, 1.0, 1.0, -1.0, -1.0, -1.0], [1.0, -1.0, -1.0, -1.0, 1.0, 1.0, 1.0]]}