{"targets": {"0": {"-1": 0.0, "0": 0.0, "1": 1.0}, "1": {"-1": 0, "0": 0, "1": 0}, "2": {"-1": 0, "0": 0, "1": 0}, "3": {"-1": 0.0, "0": 0.436, "1": 0.564}, "4": {"-1": 0.114, "0": 0.32, "1": 0.566}, "5": {"-1": 0, "0": 0, "1": 0}, "6": {"-1": 0.12, "0": 0.208, "1": 0.672}}, "board": [[0.0, 1.0, -1.0, 0.0, 0.0, 1.0, 0.0], [-1.0, 1.0, -1.0, 0.0, 0.0, -1.0, 0.0], [-1.0, -1.0, 1.0, -1.0, 0.0, -1.0, 1.0], [1.0, -1.0, 1.0, 1.0, 1.0, -1.0, 1.0], [1.0, 1.0, -1.0, -1.0, -1.0, 1.0, -1.0], [1.0, -1.0, 1.0, 1.0, -1.0, -1.0, 1.0]]}