{"targets": {"0": {"-1": 0.506, "0": 0.008, "1": 0.486}, "1": {"-1": 0, "0": 0, "1": 0}, "2": {"-1": 0.246, "0": 0.012, "1": 0.742}, "3": {"-1": 0.0, "0": 0.0, "1": 1.0}, "4": {"-1": 0.0, "0": 0.0, "1": 1.0}, "5": {"-1": 0.48, "0": 0.014, "1": 0.506}, "6": {"-1": 0.364, "0": 0.008, "1": 0.628}}, "board": [[0.0, -1.0, 0.0, 0.0, 0.0, 0.0, 0.0], [0.0, -1.0, -1.0, 0.0, 0.0, 1.0, 0.0], [-1.0, 1.0, -1.0, 0.0, 1.0, 1.0, 0.0], [1.0, -1.0, -1.0, 0.0, 1.0, -1.0, 0.0], [-1.0, -1.0, 1.0, -1.0, 1.0, -1.0, 1.0], [1.0, 1.0, -1.0, 1.0, -1.0, 1.0, 1.0]]}