{"targets": {"0": {"-1": 0.694, "0": 0.004, "1": 0.302}, "1": {"-1": 0, "0": 0, "1": 0}, "2": {"-1": 0.334, "0": 0.026, "1": 0.64}, "3": {"-1": 0.284, "0": 0.0, "1": 0.716}, "4": {"-1": 0.47, "0": 0.02, "1": 0.51}, "5": {"-1": 0.596, "0": 0.01, "1": 0.394}, "6": {"-1": 0.628, "0": 0.014, "1": 0.358}}, "board": [[0.0, 1.0, 0.0, 0.0, 0.0, 0.0, 0.0], [0.0, -1.0, 0.0, 0.0, 0.0, 0.0, -1.0], [0.0, 1.0, 1.0, 0.0, -1.0, -1.0, 1.0], [0.0, -1.0, 1.0, 1.0, -1.0, 1.0, -1.0], [1.0, -1.0, -1.0, 1.0, 1.0, -1.0, 1.0], [-1.0, 1.0, 1.0, -1.0, -1.0, -1.0, 1.0]]}