{"targets": {"0": {"-1": 0.57, "0": 0.0, "1": 0.43}, "1": {"-1": 0.562, "0": 0.0, "1": 0.438}, "2": {"-1": 0.484, "0": 0.0, "1": 0.516}, "3": {"-1": 0.0, "0": 0.0, "1": 1.0}, "4": {"-1": 0.606, "0": 0.0, "1": 0.394}, "5": {"-1": 0.346, "0": 0.0, "1": 0.654}, "6": {"-1": 0.548, "0": 0.0, "1": 0.452}}, "board": [[0.0, 0.0, 0.0, 0.0, 0.0, 0.0, 0.0], [1.0, 0.0, 0.0, 0.0, -1.0, 0.0, -1.0], [-1.0, 0.0, 1.0, 0.0, 1.0, -1.0, -1.0], [-1.0, 0.0, 1.0, 1.0, -1.0, -1.0, 1.0], [1.0, 1.0, -1.0, 1.0, -1.0, -1.0, -1.0], [1.0, 1.0, -1.0, 1.0, 1.0, 1.0, -1.0]]}