{"targets": {"0": {"-1": 0.596, "0": 0.0, "1": 0.404}, "1": {"-1": 0.34, "0": 0.0, "1": 0.66}, "2": {"-1": 0.694, "0": 0.0, "1": 0.306}, "3": {"-1": 0, "0": 0, "1": 0}, "4": {"-1": 0.0, "0": 0.0, "1": 1.0}, "5": {"-1": 0.0, "0": 0.0, "1": 1.0}, "6": {"-1": 0.556, "0": 0.002, "1": 0.442}}, "board": [[0.0, 0.0, 0.0, -1.0, 0.0, 0.0, 0.0], [0.0, 0.0, 0.0, 1.0, 0.0, 0.0, 0.0], [0.0, -1.0, 0.0, -1.0, 0.0, 0.0, 0.0], [0.0, -1.0, 0.0, -1.0, 1.0, 1.0, -1.0], [-1.0, -1.0, 0.0, 1.0, -1.0, 1.0, 1.0], [-1.0, 1.0, 1.0, 1.0, -1.0, 1.0, 1.0]]}