{"targets": {"0": {"-1": 0.598, "0": 0.238, "1": 0.164}, "1": {"-1": 0, "0": 0, "1": 0}, "2": {"-1": 0, "0": 0, "1": 0}, "3": {"-1": 0.124, "0": 0.116, "1": 0.76}, "4": {"-1": 0, "0": 0, "1": 0}, "5": {"-1": 0, "0": 0, "1": 0}, "6": {"-1": 0.604, "0": 0.038, "1": 0.358}}, "board": [[0.0, -1.0, 1.0, 0.0, 1.0, -1.0, 0.0], [0.0, 1.0, -1.0, -1.0, -1.0, 1.0, 0.0], [0.0, 1.0, -1.0, 1.0, -1.0, -1.0, 1.0], [-1.0, 1.0, 1.0, -1.0, 1.0, 1.0, -1.0], [-1.0, -1.0, -1.0, 1.0, -1.0, -1.0, 1.0], [1.0, 1.0, 1.0, -1.0, -1.0, 1.0, 1.0]]}