{"targets": {"0": {"-1": 0.95, "0": 0.016, "1": 0.034}, "1": {"-1": 0.92, "0": 0.038, "1": 0.042}, "2": {"-1": 0.888, "0": 0.04, "1": 0.072}, "3": {"-1": 0.866, "0": 0.052, "1": 0.082}, "4": {"-1": 0.932, "0": 0.024, "1": 0.044}, "5": {"-1": 0.938, "0": 0.03, "1": 0.032}, "6": {"-1": 0, "0": 0, "1": 0}}, "board": [[0.0, 0.0, 0.0, 0.0, 0.0, 0.0, 1.0], [0.0, 0.0, 0.0, 0.0, 0.0, 1.0, -1.0], [0.0, -1.0, 0.0, -1.0, -1.0, 1.0, 1.0], [0.0, -1.0, 0.0, -1.0, 1.0, -1.0, -1.0], [0.0, 1.0, 1.0, -1.0, -1.0, 1.0, 1.0], [-1.0, 1.0, -1.0, 1.0, 1.0, -1.0, 1.0]]}