{"targets": {"0": {"-1": 0.0, "0": 0.0, "1": 1.0}, "1": {"-1": 0.088, "0": 0.024, "1": 0.888}, "2": {"-1": 0.0, "0": 0.0, "1": 1.0}, "3": {"-1": 0, "0": 0, "1": 0}, "4": {"-1": 0.006, "0": 0.014, "1": 0.98}, "5": {"-1": 0.0, "0": 0.0, "1": 1.0}, "6": {"-1": 0.056, "0": 0.006, "1": 0.938}}, "board": [[0.0, 0.0, 0.0, -1.0, 0.0, 0.0, 0.0], [0.0, 0.0, 0.0, 1.0, 0.0, 0.0, 0.0], [1.0, 1.0, 0.0, -1.0, 0.0, 0.0, 0.0], [-1.0, -1.0, 1.0, 1.0, 1.0, -1.0, 1.0], [-1.0, -1.0, -1.0, 1.0, 1.0, 1.0, -1.0], [-1.0, -1.0, 1.0, -1.0, -1.0, 1.0, 1.0]]}