{"targets": {"0": {"-1": 0.746, "0": 0.0, "1": 0.254}, "1": {"-1": 0.764, "0": 0.0, "1": 0.236}, "2": {"-1": 0.502, "0": 0.0, "1": 0.498}, "3": {"-1": 0.754, "0": 0.0, "1": 0.246}, "4": {"-1": 0.52, "0": 0.0, "1": 0.48}, "5": {"-1": 0.724, "0": 0.0, "1": 0.276}, "6": {"-1": 0.792, "0": 0.0, "1": 0.208}}, "board": [[0.0, 0.0, 0.0, 0.0, 0.0, 0.0, 0.0], [0.0, 0.0, 0.0, 0.0, 0.0, 0.0, 0.0], [0.0, 0.0, 0.0, -1.0, 0.0, 0.0, 0.0], [0.0, 0.0, 0.0, 1.0, 1.0, 0.0, -1.0], [1.0, -1.0, 0.0, -1.0, -1.0, 0.0, 1.0], [-1.0, 1.0, 1.0, -1.0, 1.0, 1.0, -1.0]]}