{"targets": {"0": {"-1": 0.45, "0": 0.008, "1": 0.542}, "1": {"-1": 0, "0": 0, "1": 0}, "2": {"-1": 0.548, "0": 0.02, "1": 0.432}, "3": {"-1": 0.438, "0": 0.012, "1": 0.55}, "4": {"-1": 0.448, "0": 0.008, "1": 0.544}, "5": {"-1": 0, "0": 0, "1": 0}, "6": {"-1": 0.27, "0": 0.014, "1": 0.716}}, "board": [[0.0, -1.0, 0.0, 0.0, 0.0, 1.0, 0.0], [0.0, -1.0, -1.0, 0.0, 0.0, 1.0, 0.0], [0.0, -1.0, 1.0, 0.0, 0.0, -1.0, 0.0], [0.0, 1.0, -1.0, -1.0, 0.0, 1.0, 1.0], [1.0, 1.0, -1.0, 1.0, 0.0, -1.0, -1.0], [-1.0, -1.0, 1.0, 1.0, 1.0, -1.0, 1.0]]}