{"targets": {"0": {"-1": 0.98, "0": 0.0, "1": 0.02}, "1": {"-1": 0, "0": 0, "1": 0}, "2": {"-1": 0, "0": 0, "1": 0}, "3": {"-1": 0.646, "0": 0.126, "1": 0.228}, "4": {"-1": 0, "0": 0, "1": 0}, "5": {"-1": 0.82, "0": 0.136, "1": 0.044}, "6": {"-1": 0.72, "0": 0.144, "1": 0.136}}, "board": [[0.0, 1.0, 1.0, 0.0, 1.0, 0.0, 0.0], [1.0, -1.0, -1.0, 0.0, -1.0, 0.0, 0.0], [-1.0, 1.0, 1.0, 1.0, -1.0, 0.0, -1.0], [1.0, -1.0, -1.0, 1.0, 1.0, 1.0, -1.0], [1.0, -1.0, -1.0, -1.0, 1.0, -1.0, -1.0], [1.0, 1.0, -1.0, 1.0, -1.0, -1.0, 1.0]]}