{"targets": {"0": {"-1": 0.67, "0": 0.0, "1": 0.33}, "1": {"-1": 0.792, "0": 0.0, "1": 0.208}, "2": {"-1": 0.806, "0": 0.0, "1": 0.194}, "3": {"-1": 0.418, "0": 0.0, "1": 0.582}, "4": {"-1": 0.776, "0": 0.0, "1": 0.224}, "5": {"-1": 0.516, "0": 0.0, "1": 0.484}, "6": {"-1": 0.782, "0": 0.0, "1": 0.218}}, "board": [[0.0, 0.0, 0.0, 0.0, 0.0, 0.0, 0.0], [0.0, 0.0, -1.0, 0.0, 0.0, 0.0, 1.0], [1.0, -1.0, 1.0, 0.0, -1.0, 0.0, 1.0], [1.0, 1.0, 1.0, 0.0, 1.0, -1.0, -1.0], [-1.0, -1.0, -1.0, 0.0, 1.0, -1.0, 1.0], [1.0, 1.0, -1.0, -1.0, 1.0, -1.0, -1.0]]}