{"targets": {"0": {"-1": 0.826, "0": 0.0, "1": 0.174}, "1": {"-1": 0.792, "0": 0.0, "1": 0.208}, "2": {"-1": 0, "0": 0, "1": 0}, "3": {"-1": 0.748, "0": 0.0, "1": 0.252}, "4": {"-1": 0.474, "0": 0.0, "1": 0.526}, "5": {"-1": 0.62, "0": 0.0, "1": 0.38}, "6": {"-1": 0.0, "0": 0.0, "1": 1.0}}, "board": [[0.0, 0.0, 1.0, 0.0, 0.0, 0.0, 0.0], [0.0, 1.0, -1.0, 0.0, 0.0, 0.0, 0.0], [0.0, 1.0, 1.0, 0.0, 0.0, 1.0, 0.0], [0.0, -1.0, -1.0, -1.0, 0.0, 1.0, -1.0], [0.0, 1.0, 1.0, -1.0, 1.0, -1.0, -1.0], [1.0, -1.0, -1.0, 1.0, 1.0, -1.0, -1.0]]}