{"targets": {"0": {"-1": 0.76, "0": 0.0, "1": 0.24}, "1": {"-1": 0.756, "0": 0.01, "1": 0.234}, "2": {"-1": 0.874, "0": 0.004, "1": 0.122}, "3": {"-1": 0.876, "0": 0.0, "1": 0.124}, "4": {"-1": 0.914, "0": 0.012, "1": 0.074}, "5": {"-1": 0.77, "0": 0.004, "1": 0.226}, "6": {"-1": 0.898, "0": 0.0, "1": 0.102}}, "board": [[0.0, 0.0, 0.0, 0.0, 0.0, 0.0, 0.0], [0.0, 0.0, 0.0, 0.0, 1.0, 0.0, 0.0], [0.0, 0.0, 0.0, -1.0, 1.0, 0.0, 0.0], [0.0, 0.0, 0.0, 1.0, -1.0, 0.0, 0.0], [1.0, 0.0, -1.0, -1.0, -1.0, 0.0, 0.0], [1.0, 1.0, 1.0, -1.0, 1.0, -1.0, -1.0]]}