{"targets": {"0": {"-1": 0.752, "0": 0.036, "1": 0.212}, "1": {"-1": 0.866, "0": 0.004, "1": 0.13}, "2": {"-1": 0.0, "0": 0.0, "1": 1.0}, "3": {"-1": 0.758, "0": 0.034, "1": 0.208}, "4": {"-1": 0.908, "0": 0.014, "1": 0.078}, "5": {"-1": 0, "0": 0, "1": 0}, "6": {"-1": 0.736, "0": 0.038, "1": 0.226}}, "board": [[0.0, 0.0, 0.0, 0.0, 0.0, 1.0, 0.0], [0.0, -1.0, 0.0, 1.0, -1.0, 1.0, 0.0], [-1.0, -1.0, 0.0, 1.0, 1.0, -1.0, -1.0], [-1.0, 1.0, 1.0, -1.0, 1.0, 1.0, -1.0], [-1.0, -1.0, 1.0, 1.0, 1.0, -1.0, -1.0], [1.0, -1.0, 1.0, 1.0, -1.0, -1.0, 1.0]]}