{"targets": {"0": {"-1": 0.78, "0": 0.0, "1": 0.22}, "1": {"-1": 0.642, "0": 0.0, "1": 0.358}, "2": {"-1": 0.8, "0": 0.0, "1": 0.2}, "3": {"-1": 0.514, "0": 0.0, "1": 0.486}, "4": {"-1": 0.816, "0": 0.0, "1": 0.184}, "5": {"-1": 0.0, "0": 0.0, "1": 1.0}, "6": {"-1": 0.808, "0": 0.0, "1": 0.192}}, "board": [[0.0, 0.0, 0.0, 0.0, 0.0, 0.0, 0.0], [0.0, 0.0, 0.0, 0.0, 0.0, 0.0, 0.0], [-1.0, 0.0, 1.0, -1.0, 0.0, 0.0, 1.0], [-1.0, 0.0, -1.0, -1.0, 0.0, 0.0, -1.0], [1.0, 1.0, -1.0, -1.0, 1.0, 1.0, 1.0], [1.0, -1.0, 1.0, 1.0, -1.0, 1.0, -1.0]]}