{"targets": {"0": {"-1": 0.876, "0": 0.004, "1": 0.12}, "1": {"-1": 0.768, "0": 0.0, "1": 0.232}, "2": {"-1": 0.848, "0": 0.0, "1": 0.152}, "3": {"-1": 0.836, "0": 0.0, "1": 0.164}, "4": {"-1": 0.744, "0": 0.0, "1": 0.256}, "5": {"-1": 0.78, "0": 0.004, "1": 0.216}, "6": {"-1": 0.868, "0": 0.0, "1": 0.132}}, "board": [[0.0, 0.0, 0.0, 0.0, 0.0, 0.0, 0.0], [0.0, 0.0, 0.0, 0.0, 0.0, 0.0, 0.0], [0.0, 0.0, 0.0, 0.0, 0.0, 0.0, 0.0], [0.0, 0.0, 0.0, 0.0, -1.0, 0.0, 0.0], [0.0, 1.0, 0.0, -1.0, -1.0, 0.0, -1.0], [1.0, 1.0, -1.0, 1.0, -1.0, 1.0, 1.0]]}