{"targets": {"0": {"-1": 0.66, "0": 0.0, "1": 0.34}, "1": {"-1": 0.526, "0": 0.0, "1": 0.474}, "2": {"-1": 0.774, "0": 0.0, "1": 0.226}, "3": {"-1": 0, "0": 0, "1": 0}, "4": {"-1": 0.682, "0": 0.0, "1": 0.318}, "5": {"-1": 0.418, "0": 0.0, "1": 0.582}, "6": {"-1": 0, "0": 0, "1": 0}}, "board": [[0.0, 0.0, 0.0, -1.0, 0.0, 0.0, -1.0], [0.0, 0.0, 1.0, 1.0, 0.0, 0.0, 1.0], [1.0, 1.0, 1.0, -1.0, 0.0, 0.0, -1.0], [-1.0, -1.0, -1.0, 1.0, -1.0, 0.0, -1.0], [1.0, -1.0, 1.0, -1.0, -1.0, 1.0, 1.0], [1.0, -1.0, -1.0, -1.0, 1.0, 1.0, 1.0]]}