{"targets": {"0": {"-1": 0.376, "0": 0.0, "1": 0.624}, "1": {"-1": 0.52, "0": 0.024, "1": 0.456}, "2": {"-1": 0, "0": 0, "1": 0}, "3": {"-1": 0, "0": 0, "1": 0}, "4": {"-1": 0.448, "0": 0.072, "1": 0.48}, "5": {"-1": 0.0, "0": 0.0, "1": 1.0}, "6": {"-1": 0, "0": 0, "1": 0}}, "board": [[0.0, 0.0, -1.0, -1.0, 0.0, 0.0, 1.0], [0.0, 0.0, -1.0, -1.0, -1.0, 1.0, 1.0], [0.0, 0.0, 1.0, 1.0, -1.0, 1.0, 1.0], [1.0, 0.0, -1.0, -1.0, 1.0, 1.0, -1.0], [-1.0, 0.0, 1.0, -1.0, 1.0, -1.0, -1.0], [1.0, -1.0, 1.0, -1.0, 1.0, 1.0, -1.0]]}