{"targets": {"0": {"-1": 0.268, "0": 0.002, "1": 0.73}, "1": {"-1": 0.288, "0": 0.0, "1": 0.712}, "2": {"-1": 0.29, "0": 0.002, "1": 0.708}, "3": {"-1": 0.284, "0": 0.0, "1": 0.716}, "4": {"-1": 0.0, "0": 0.0, "1": 1.0}, "5": {"-1": 0.22, "0": 0.0, "1": 0.78}, "6": {"-1": 0.376, "0": 0.002, "1": 0.622}}, "board": [[0.0, 0.0, 0.0, 0.0, 0.0, 0.0, 0.0], [0.0, 0.0, 0.0, 0.0, 0.0, 0.0, 1.0], [0.0, 0.0, 0.0, 0.0, 0.0, 1.0, -1.0], [1.0, 0.0, 0.0, 0.0, 0.0, 1.0, -1.0], [-1.0, 0.0, 0.0, 1.0, -1.0, -1.0, 1.0], [1.0, 1.0, -1.0, -1.0, -1.0, 1.0, -1.0]]}