{"targets": {"0": {"-1": 0, "0": 0, "1": 0}, "1": {"-1": 0.486, "0": 0.052, "1": 0.462}, "2": {"-1": 0.322, "0": 0.106, "1": 0.572}, "3": {"-1": 0, "0": 0, "1": 0}, "4": {"-1": 0.0, "0": 0.0, "1": 1.0}, "5": {"-1": 0, "0": 0, "1": 0}, "6": {"-1": 0.384, "0": 0.068, "1": 0.548}}, "board": [[1.0, 0.0, 0.0, -1.0, 0.0, -1.0, 0.0], [-1.0, 0.0, 0.0, -1.0, 0.0, -1.0, 0.0], [-1.0, 0.0, 1.0, 1.0, 0.0, -1.0, 0.0], [1.0, 0.0, -1.0, -1.0, 1.0, 1.0, 1.0], [1.0, -1.0, 1.0, 1.0, 1.0, -1.0, -1.0], [1.0, 1.0, -1.0, -1.0, 1.0, -1.0, 1.0]]}