{"targets": {"0": {"-1": 0, "0": 0, "1": 0}, "1": {"-1": 0.216, "0": 0.0, "1": 0.784}, "2": {"-1": 0.0, "0": 0.0, "1": 1.0}, "3": {"-1": 0.0, "0": 0.0, "1": 1.0}, "4": {"-1": 0, "0": 0, "1": 0}, "5": {"-1": 0.268, "0": 0.0, "1": 0.732}, "6": {"-1": 0.18, "0": 0.0, "1": 0.82}}, "board": [[1.0, 0.0, 0.0, 0.0, -1.0, 0.0, 0.0], [-1.0, 1.0, 0.0, 0.0, -1.0, 0.0, 0.0], [-1.0, -1.0, 0.0, 0.0, 1.0, 0.0, 0.0], [-1.0, 1.0, 0.0, 1.0, -1.0, -1.0, 0.0], [1.0, -1.0, 0.0, 1.0, 1.0, 1.0, -1.0], [1.0, -1.0, 1.0, 1.0, 1.0, -1.0, -1.0]]}