{"targets": {"0": {"-1": 0, "0": 0, "1": 0}, "1": {"-1": 0.0, "0": 0.0, "1": 1.0}, "2": {"-1": 0, "0": 0, "1": 0}, "3": {"-1": 0, "0": 0, "1": 0}, "4": {"-1": 0.108, "0": 0.12, "1": 0.772}, "5": {"-1": 0.306, "0": 0.086, "1": 0.608}, "6": {"-1": 0.328, "0": 0.05, "1": 0.622}}, "board": [[1.0, 0.0, -1.0, -1.0, 0.0, 0.0, 0.0], [1.0, 0.0, 1.0, 1.0, 0.0, -1.0, 0.0], [1.0, 0.0, -1.0, -1.0, 0.0, 1.0, 0.0], [-1.0, 1.0, 1.0, -1.0, -1.0, -1.0, 1.0], [-1.0, -1.0, 1.0, 1.0, 1.0, -1.0, -1.0], [1.0, 1.0, -1.0, -1.0, -1.0, 1.0, 1.0]]}