{"targets": {"0": {"-1": 0, "0": 0, "1": 0}, "1": {"-1": 0, "0": 0, "1": 0}, "2": {"-1": 0.0, "0": 0.218, "1": 0.782}, "3": {"-1": 0, "0": 0, "1": 0}, "4": {"-1": 0.0, "0": 0.284, "1": 0.716}, "5": {"-1": 0.178, "0": 0.41, "1": 0.412}, "6": {"-1": 0.256, "0": 0.176, "1": 0.568}}, "board": [[1.0, -1.0, 0.0, -1.0, 0.0, 0.0, 0.0], [-1.0, 1.0, 1.0, -1.0, 1.0, 0.0, 1.0], [-1.0, 1.0, -1.0, 1.0, 1.0, 0.0, -1.0], [-1.0, 1.0, -1.0, 1.0, -1.0, 1.0, -1.0], [1.0, -1.0, 1.0, -1.0, -1.0, -1.0, 1.0], [1.0, -1.0, 1.0, 1.0, -1.0, 1.0, -1.0]]}