{"targets": {"0": {"-1": 0, "0": 0, "1": 0}, "1": {"-1": 0.586, "0": 0.06, "1": 0.354}, "2": {"-1": 0, "0": 0, "1": 0}, "3": {"-1": 0.134, "0": 0.066, "1": 0.8}, "4": {"-1": 0, "0": 0, "1": 0}, "5": {"-1": 0, "0": 0, "1": 0}, "6": {"-1": 0.5, "0": 0.142, "1": 0.358}}, "board": [[1.0, 0.0, 1.0, 0.0, -1.0, -1.0, 0.0], [1.0, -1.0, -1.0, -1.0, 1.0, -1.0, 0.0], [-1.0, 1.0, 1.0, 1.0, -1.0, 1.0, 0.0], [-1.0, 1.0, -1.0, -1.0, -1.0, 1.0, 0.0], [1.0, -1.0, 1.0, 1.0, -1.0, -1.0, -1.0], [-1.0, 1.0, 1.0, -1.0, 1.0, 1.0, 1.0]]}