{"targets": {"0": {"-1": 0, "0": 0, "1": 0}, "1": {"-1": 0.0, "0": 0.726, "1": 0.274}, "2": {"-1": 0, "0": 0, "1": 0}, "3": {"-1": 0, "0": 0, "1": 0}, "4": {"-1": 0, "0": 0, "1": 0}, "5": {"-1": 0.0, "0": 0.276, "1": 0.724}, "6": {"-1": 0.0, "0": 0.74, "1": 0.26}}, "board": [[1.0, 0.0, -1.0, 1.0, -1.0, 0.0, 0.0], [1.0, 1.0, -1.0, 1.0, 1.0, 0.0, 0.0], [-1.0, -1.0, 1.0, -1.0, 1.0, -1.0, 0.0], [-1.0, -1.0, 1.0, -1.0, 1.0, 1.0, 1.0], [1.0, -1.0, -1.0, 1.0, -1.0, -1.0, -1.0], [-1.0, 1.0, -1.0, 1.0, 1.0, 1.0, -1.0]]}