{"targets": {"0": {"-1": 0, "0": 0, "1": 0}, "1": {"-1": 0, "0": 0, "1": 0}, "2": {"-1": 0.924, "0": 0.0, "1": 0.076}, "3": {"-1": 0.938, "0": 0.0, "1": 0.062}, "4": {"-1": 0.904, "0": 0.0, "1": 0.096}, "5": {"-1": 0.92, "0": 0.0, "1": 0.08}, "6": {"-1": 0.994, "0": 0.0, "1": 0.006}}, "board": [[1.0, -1.0, 0.0, 0.0, 0.0, 0.0, 0.0], [1.0, 1.0, 0.0, 0.0, 0.0, 0.0, 0.0], [-1.0, -1.0, 0.0, 1.0, 0.0, 0.0, -1.0], [1.0, 1.0, -1.0, -1.0, -1.0, 0.0, 1.0], [-1.0, 1.0, -1.0, -1.0, 1.0, 1.0, 1.0], [1.0, -1.0, -1.0, -1.0, 1.0, -1.0, 1.0]]}