{"targets": {"0": {"-1": 0, "0": 0, "1": 0}, "1": {"-1": 0.718, "0": 0.038, "1": 0.244}, "2": {"-1": 0.53, "0": 0.104, "1": 0.366}, "3": {"-1": 0.578, "0": 0.08, "1": 0.342}, "4": {"-1": 0.71, "0": 0.052, "1": 0.238}, "5": {"-1": 0.578, "0": 0.024, "1": 0.398}, "6": {"-1": 0.53, "0": 0.088, "1": 0.382}}, "board": [[1.0, 0.0, 0.0, 0.0, 0.0, 0.0, 0.0], [-1.0, 1.0, 0.0, 0.0, -1.0, 0.0, 0.0], [-1.0, 1.0, 0.0, -1.0, 1.0, 0.0, 0.0], [1.0, -1.0, 0.0, -1.0, 1.0, 0.0, 0.0], [1.0, 1.0, -1.0, 1.0, 1.0, -1.0, -1.0], [1.0, -1.0, -1.0, 1.0, -1.0, 1.0, -1.0]]}