{"targets": {"0": {"-1": 0, "0": 0, "1": 0}, "1": {"-1": 0.792, "0": 0.024, "1": 0.184}, "2": {"-1": 0.516, "0": 0.026, "1": 0.458}, "3": {"-1": 0.0, "0": 0.0, "1": 1.0}, "4": {"-1": 0, "0": 0, "1": 0}, "5": {"-1": 0.712, "0": 0.01, "1": 0.278}, "6": {"-1": 0, "0": 0, "1": 0}}, "board": [[1.0, 0.0, 0.0, 0.0, -1.0, 0.0, -1.0], [-1.0, -1.0, 0.0, 0.0, 1.0, 0.0, 1.0], [-1.0, 1.0, -1.0, 0.0, 1.0, -1.0, -1.0], [1.0, 1.0, -1.0, 0.0, -1.0, 1.0, -1.0], [1.0, -1.0, -1.0, 0.0, 1.0, 1.0, 1.0], [-1.0, -1.0, 1.0, 1.0, -1.0, 1.0, 1.0]]}