{"targets": {"0": {"-1": 0, "0": 0, "1": 0}, "1": {"-1": 0.146, "0": 0.2, "1": 0.654}, "2": {"-1": 0, "0": 0, "1": 0}, "3": {"-1": 0.0, "0": 0.0, "1": 1.0}, "4": {"-1": 0, "0": 0, "1": 0}, "5": {"-1": 0.0, "0": 0.0, "1": 1.0}, "6": {"-1": 0.14, "0": 0.18, "1": 0.68}}, "board": [[1.0, 0.0, -1.0, 0.0, 1.0, 0.0, 0.0], [1.0, -1.0, 1.0, 0.0, -1.0, 0.0, 0.0], [-1.0, -1.0, 1.0, -1.0, 1.0, 0.0, -1.0], [1.0, 1.0, 1.0, -1.0, 1.0, 1.0, -1.0], [-1.0, 1.0, -1.0, 1.0, -1.0, -1.0, 1.0], [-1.0, -1.0, 1.0, -1.0, 1.0, -1.0, 1.0]]}