{"targets": {"0": {"-1": 0, "0": 0, "1": 0}, "1": {"-1": 0.484, "0": 0.308, "1": 0.208}, "2": {"-1": 0, "0": 0, "1": 0}, "3": {"-1": 0.0, "0": 0.512, "1": 0.488}, "4": {"-1": 0.53, "0": 0.306, "1": 0.164}, "5": {"-1": 0.518, "0": 0.0, "1": 0.482}, "6": {"-1": 0, "0": 0, "1": 0}}, "board": [[1.0, 0.0, -1.0, 0.0, 0.0, 0.0, -1.0], [-1.0, -1.0, 1.0, 0.0, 1.0, 0.0, 1.0], [1.0, 1.0, -1.0, -1.0, -1.0, 1.0, 1.0], [-1.0, -1.0, -1.0, 1.0, 1.0, -1.0, -1.0], [1.0, -1.0, 1.0, -1.0, 1.0, -1.0, 1.0], [1.0, -1.0, 1.0, 1.0, 1.0, -1.0, -1.0]]}