{"targets": {"0": {"-1": 0, "0": 0, "1": 0}, "1": {"-1": 0.564, "0": 0.0, "1": 0.436}, "2": {"-1": 0, "0": 0, "1": 0}, "3": {"-1": 0.0, "0": 0.0, "1": 1.0}, "4": {"-1": 0, "0": 0, "1": 0}, "5": {"-1": 0.596, "0": 0.028, "1": 0.376}, "6": {"-1": 0.544, "0": 0.01, "1": 0.446}}, "board": [[1.0, 0.0, -1.0, 0.0, 1.0, 0.0, 0.0], [1.0, 0.0, 1.0, 0.0, -1.0, -1.0, 0.0], [1.0, 1.0, -1.0, 0.0, -1.0, 1.0, 1.0], [-1.0, -1.0, -1.0, 0.0, 1.0, 1.0, -1.0], [-1.0, -1.0, 1.0, 0.0, -1.0, -1.0, 1.0], [-1.0, 1.0, 1.0, -1.0, 1.0, -1.0, 1.0]]}