{"targets": {"0": {"-1": 0, "0": 0, "1": 0}, "1": {"-1": 0.738, "0": 0.0, "1": 0.262}, "2": {"-1": 0.93, "0": 0.0, "1": 0.07}, "3": {"-1": 0, "0": 0, "1": 0}, "4": {"-1": 0.92, "0": 0.0, "1": 0.08}, "5": {"-1": 0.716, "0": 0.0, "1": 0.284}, "6": {"-1": 0.9, "0": 0.0, "1": 0.1}}, "board": [[1.0, 0.0, 0.0, -1.0, 0.0, 0.0, 0.0], [1.0, 0.0, -1.0, -1.0, 1.0, 0.0, 0.0], [1.0, 0.0, 1.0, 1.0, -1.0, 0.0, 0.0], [-1.0, 0.0, -1.0, -1.0, 1.0, 0.0, 0.0], [-1.0, -1.0, -1.0, 1.0, 1.0, -1.0, -1.0], [1.0, 1.0, 1.0, -1.0, -1.0, 1.0, 1.0]]}