{"targets": {"0": {"-1": 0, "0": 0, "1": 0}, "1": {"-1": 0.0, "0": 0.0, "1": 1.0}, "2": {"-1": 0.464, "0": 0.018, "1": 0.518}, "3": {"-1": 0.54, "0": 0.016, "1": 0.444}, "4": {"-1": 0.308, "0": 0.034, "1": 0.658}, "5": {"-1": 0.61, "0": 0.022, "1": 0.368}, "6": {"-1": 0.582, "0": 0.02, "1": 0.398}}, "board": [[1.0, 0.0, 0.0, 0.0, 0.0, 0.0, 0.0], [1.0, 0.0, 0.0, 0.0, 0.0, 0.0, 0.0], [-1.0, 0.0, 1.0, -1.0, 0.0, 0.0, 0.0], [-1.0, -1.0, 1.0, -1.0, 0.0, 0.0, 1.0], [1.0, 1.0, -1.0, 1.0, -1.0, -1.0, -1.0], [-1.0, 1.0, -1.0, 1.0, 1.0, 1.0, -1.0]]}