{"targets": {"0": {"-1": 0, "0": 0, "1": 0}, "1": {"-1": 0, "0": 0, "1": 0}, "2": {"-1": 0.47, "0": 0.128, "1": 0.402}, "3": {"-1": 0, "0": 0, "1": 0}, "4": {"-1": 0.0, "0": 0.0, "1": 1.0}, "5": {"-1": 0, "0": 0, "1": 0}, "6": {"-1": 0.22, "0": 0.152, "1": 0.628}}, "board": [[-1.0, -1.0, 0.0, -1.0, 0.0, 1.0, 0.0], [1.0, -1.0, 0.0, 1.0, 0.0, 1.0, 0.0], [-1.0, 1.0, 1.0, 1.0, 0.0, -1.0, 0.0], [1.0, -1.0, -1.0, -1.0, 1.0, 1.0, 1.0], [1.0, -1.0, -1.0, 1.0, -1.0, -1.0, -1.0], [1.0, 1.0, -1.0, 1.0, -1.0, -1.0, 1.0]]}