{"targets": {"0": {"-1": 0, "0": 0, "1": 0}, "1": {"-1": 0, "0": 0, "1": 0}, "2": {"-1": 0.328, "0": 0.014, "1": 0.658}, "3": {"-1": 0.238, "0": 0.11, "1": 0.652}, "4": {"-1": 0.0, "0": 0.0, "1": 1.0}, "5": {"-1": 0.292, "0": 0.072, "1": 0.636}, "6": {"-1": 0.418, "0": 0.034, "1": 0.548}}, "board": [[-1.0, -1.0, 0.0, 0.0, 0.0, 0.0, 0.0], [-1.0, -1.0, 0.0, 1.0, 0.0, 0.0, 0.0], [1.0, 1.0, 1.0, -1.0, 0.0, -1.0, 1.0], [1.0, -1.0, -1.0, -1.0, 0.0, -1.0, -1.0], [-1.0, -1.0, 1.0, 1.0, 0.0, 1.0, 1.0], [1.0, 1.0, 1.0, -1.0, 1.0, -1.0, 1.0]]}