{"targets": {"0": {"-1": 0, "0": 0, "1": 0}, "1": {"-1": 0, "0": 0, "1": 0}, "2": {"-1": 0, "0": 0, "1": 0}, "3": {"-1": 0.0, "0": 0.0, "1": 1.0}, "4": {"-1": 0.178, "0": 0.034, "1": 0.788}, "5": {"-1": 0.148, "0": 0.022, "1": 0.83}, "6": {"-1": 0.214, "0": 0.022, "1": 0.764}}, "board": [[-1.0, -1.0, -1.0, 0.0, 0.0, 0.0, 0.0], [1.0, 1.0, -1.0, 0.0, -1.0, 0.0, 0.0], [1.0, -1.0, 1.0, 0.0, 1.0, 0.0, 0.0], [1.0, 1.0, -1.0, 0.0, 1.0, 0.0, 0.0], [-1.0, -1.0, -1.0, 1.0, 1.0, -1.0, 0.0], [-1.0, 1.0, 1.0, 1.0, -1.0, 1.0, -1.0]]}