{"targets": {"0": {"-1": 0, "0": 0, "1": 0}, "1": {"-1": 0.668, "0": 0.03, "1": 0.302}, "2": {"-1": 0.614, "0": 0.026, "1": 0.36}, "3": {"-1": 0.408, "0": 0.018, "1": 0.574}, "4": {"-1": 0.666, "0": 0.038, "1": 0.296}, "5": {"-1": 0.666, "0": 0.03, "1": 0.304}, "6": {"-1": 0.638, "0": 0.024, "1": 0.338}}, "board": [[-1.0, 0.0, 0.0, 0.0, 0.0, 0.0, 0.0], [1.0, 0.0, 0.0, 0.0, 0.0, 0.0, 0.0], [1.0, 0.0, 0.0, 0.0, 1.0, 0.0, 0.0], [-1.0, 0.0, -1.0, 0.0, -1.0, 0.0, 0.0], [1.0, 0.0, -1.0, 1.0, -1.0, 0.0, 0.0], [1.0, -1.0, 1.0, 1.0, -1.0, -1.0, 1.0]]}