{"targets": {"0": {"-1": 0, "0": 0, "1": 0}, "1": {"-1": 0.772, "0": 0.01, "1": 0.218}, "2": {"-1": 0, "0": 0, "1": 0}, "3": {"-1": 0.896, "0": 0.0, "1": 0.104}, "4": {"-1": 0.916, "0": 0.026, "1": 0.058}, "5": {"-1": 0.868, "0": 0.024, "1": 0.108}, "6": {"-1": 0.858, "0": 0.0, "1": 0.142}}, "board": [[-1.0, 0.0, 1.0, 0.0, 0.0, 0.0, 0.0], [1.0, 0.0, 1.0, -1.0, 1.0, 0.0, 0.0], [-1.0, 0.0, -1.0, -1.0, -1.0, 0.0, 0.0], [1.0, -1.0, 1.0, 1.0, -1.0, 0.0, 1.0], [1.0, -1.0, -1.0, -1.0, 1.0, 1.0, -1.0], [-1.0, 1.0, 1.0, 1.0, -1.0, -1.0, 1.0]]}