{"targets": {"0": {"-1": 0, "0": 0, "1": 0}, "1": {"-1": 0.0, "0": 0.0, "1": 1.0}, "2": {"-1": 0, "0": 0, "1": 0}, "3": {"-1": 0.398, "0": 0.014, "1": 0.588}, "4": {"-1": 0.606, "0": 0.012, "1": 0.382}, "5": {"-1": 0.356, "0": 0.0, "1": 0.644}, "6": {"-1": 0, "0": 0, "1": 0}}, "board": [[-1.0, 0.0, -1.0, 0.0, 0.0, 0.0, -1.0], [1.0, 0.0, -1.0, 1.0, 0.0, 0.0, 1.0], [-1.0, 0.0, 1.0, -1.0, 0.0, 0.0, 1.0], [1.0, 1.0, 1.0, -1.0, 0.0, -1.0, -1.0], [-1.0, -1.0, 1.0, 1.0, 0.0, -1.0, 1.0], [1.0, -1.0, -1.0, 1.0, -1.0, 1.0, 1.0]]}