{"targets": {"0": {"-1": 0, "0": 0, "1": 0}, "1": {"-1": 0.128, "0": 0.586, "1": 0.286}, "2": {"-1": 0, "0": 0, "1": 0}, "3": {"-1": 0, "0": 0, "1": 0}, "4": {"-1": 0.0, "0": 0.0, "1": 1.0}, "5": {"-1": 0, "0": 0, "1": 0}, "6": {"-1": 0.406, "0": 0.276, "1": 0.318}}, "board": [[-1.0, 0.0, 1.0, 1.0, 0.0, 1.0, 0.0], [-1.0, 1.0, -1.0, 1.0, 0.0, -1.0, 0.0], [1.0, 1.0, 1.0, -1.0, 0.0, -1.0, 1.0], [-1.0, -1.0, -1.0, 1.0, -1.0, 1.0, 1.0], [-1.0, -1.0, -1.0, 1.0, -1.0, 1.0, -1.0], [1.0, -1.0, 1.0, -1.0, 1.0, -1.0, 1.0]]}